hivemind_bus_client/__init__.py
hivemind_bus_client/client.py
hivemind_bus_client/decorators.py
hivemind_bus_client/encryption.py
hivemind_bus_client/exceptions.py
hivemind_bus_client/http_client.py
hivemind_bus_client/identity.py
hivemind_bus_client/message.py
hivemind_bus_client/protocol.py
hivemind_bus_client/scripts.py
hivemind_bus_client/serialization.py
hivemind_bus_client/util.py
hivemind_bus_client/version.py
hivemind_bus_client/z85b.py
hivemind_bus_client/encodings/__init__.py
hivemind_bus_client/encodings/b91.py
hivemind_bus_client/encodings/benchmark.py
hivemind_bus_client/encodings/z85b.py
hivemind_bus_client/encodings/z85p.py
hivemind_bus_client-0.4.4.dist-info/licenses/LICENSE.md
hivemind_bus_client-0.4.4.dist-info/METADATA
hivemind_bus_client-0.4.4.dist-info/WHEEL
hivemind_bus_client-0.4.4.dist-info/entry_points.txt
hivemind_bus_client-0.4.4.dist-info/top_level.txt
hivemind_bus_client-0.4.4.dist-info/RECORD
