Metadata-Version: 2.4
Name: hivemind_bus_client
Version: 0.4.4
Summary: Hivemind Websocket Client
Home-page: https://github.com/JarbasHiveMind/hivemind_websocket_client
Author: JarbasAi
Author-email: jarbasai@mailfence.com
License: Apache-2.0
Classifier: Development Status :: 4 - Beta
Classifier: Intended Audience :: Developers
Classifier: License :: OSI Approved :: Apache Software License
Classifier: Programming Language :: Python :: 3.5
Classifier: Programming Language :: Python :: 3.6
Classifier: Programming Language :: Python :: 3.7
Classifier: Programming Language :: Python :: 3.8
License-File: LICENSE.md
Requires-Dist: poorman-handshake<2.0.0,>=1.0.0
Requires-Dist: ovos_bus_client>=0.0.6a19
Requires-Dist: ovos_utils>=0.0.38
Requires-Dist: bitstring>=4.1.1
Requires-Dist: cryptography>=41.0.1
Requires-Dist: pycryptodomex>=3.18.0
Requires-Dist: pybase64
Requires-Dist: py-cpuinfo
Requires-Dist: z85base91<1.0.0,>=0.0.5
Dynamic: author
Dynamic: author-email
Dynamic: classifier
Dynamic: description
Dynamic: description-content-type
Dynamic: home-page
Dynamic: license
Dynamic: license-file
Dynamic: requires-dist
Dynamic: summary
